sleeppy/__init__.py
sleeppy/sleep.py
sleeppy/version.py
sleeppy/tests/__init__.py
sleeppy/tests/demo.py
sleeppy-0.2.1.dist-info/LICENSE.md
sleeppy-0.2.1.dist-info/METADATA
sleeppy-0.2.1.dist-info/WHEEL
sleeppy-0.2.1.dist-info/top_level.txt
sleeppy-0.2.1.dist-info/RECORD
