Metadata-Version: 2.1
Name: sleeppy
Version: 0.2.1
Summary: Python package for sleep analysis of raw accelerometer data from GeneActiv wrist watches
Home-page: http://github.com/elyiorgos/sleeppy
Author: Yiorgos Christakis
Author-email: elyiorgos@gmail.com
License: MIT
Keywords: sleep,wake,sensor,digital,wearable,python,rest,period,christakis
Platform: UNKNOWN
Classifier: Programming Language :: Python :: 2.7
Classifier: License :: OSI Approved :: MIT License
Requires-Dist: pandas (==0.23.4)
Requires-Dist: numpy (==1.16.4)
Requires-Dist: matplotlib (==2.2.4)
Requires-Dist: scipy (==1.2.2)
Requires-Dist: seaborn (==0.9.0)
Requires-Dist: bitstring (==3.1.5)
Requires-Dist: argparse (==1.1)
Requires-Dist: tables (==3.5.2)
